milauth/__init__.py
milauth/api.py
milauth/milaCoinsError.py
milauth-0.1.0.dist-info/METADATA
milauth-0.1.0.dist-info/WHEEL
milauth-0.1.0.dist-info/top_level.txt
milauth-0.1.0.dist-info/RECORD
